termyui/__init__.py
termyui/termyui.py
termyui-0.0.dist-info/METADATA
termyui-0.0.dist-info/WHEEL
termyui-0.0.dist-info/top_level.txt
termyui-0.0.dist-info/RECORD
