Metadata-Version: 2.1
Name: termyui
Version: 0.0
Requires-Dist: windows-curses
Requires-Dist: pyfiglet
Requires-Dist: termcolor
Requires-Dist: re
Requires-Dist: term-image
